enumfields/__init__.py
enumfields/admin.py
enumfields/enums.py
enumfields/fields.py
enumfields/forms.py
enumfields/drf/__init__.py
enumfields/drf/fields.py
enumfields/drf/serializers.py
django_enumfields-2.1.0.dist-info/LICENSE
django_enumfields-2.1.0.dist-info/METADATA
django_enumfields-2.1.0.dist-info/WHEEL
django_enumfields-2.1.0.dist-info/top_level.txt
django_enumfields-2.1.0.dist-info/RECORD
